bandwidth/__init__.py
bandwidth/api_client.py
bandwidth/api_response.py
bandwidth/configuration.py
bandwidth/exceptions.py
bandwidth/rest.py
bandwidth/api/__init__.py
bandwidth/api/calls_api.py
bandwidth/api/conferences_api.py
bandwidth/api/media_api.py
bandwidth/api/messages_api.py
bandwidth/api/mfa_api.py
bandwidth/api/multi_channel_api.py
bandwidth/api/phone_number_lookup_api.py
bandwidth/api/recordings_api.py
bandwidth/api/statistics_api.py
bandwidth/api/toll_free_verification_api.py
bandwidth/api/transcriptions_api.py
bandwidth/models/__init__.py
bandwidth/models/account_statistics.py
bandwidth/models/additional_denial_reason.py
bandwidth/models/address.py
bandwidth/models/answer_callback.py
bandwidth/models/async_lookup_request.py
bandwidth/models/blocked_webhook.py
bandwidth/models/bridge_complete_callback.py
bandwidth/models/bridge_target_complete_callback.py
bandwidth/models/business_entity_type_enum.py
bandwidth/models/business_registration_type_enum.py
bandwidth/models/call_direction_enum.py
bandwidth/models/call_recording_metadata.py
bandwidth/models/call_state.py
bandwidth/models/call_state_enum.py
bandwidth/models/call_transcription.py
bandwidth/models/call_transcription_detected_language_enum.py
bandwidth/models/call_transcription_metadata.py
bandwidth/models/call_transcription_response.py
bandwidth/models/call_transcription_track_enum.py
bandwidth/models/callback.py
bandwidth/models/callback_method_enum.py
bandwidth/models/card_width_enum.py
bandwidth/models/code_request.py
bandwidth/models/completed_lookup_status_enum.py
bandwidth/models/conference.py
bandwidth/models/conference_completed_callback.py
bandwidth/models/conference_created_callback.py
bandwidth/models/conference_member.py
bandwidth/models/conference_member_exit_callback.py
bandwidth/models/conference_member_join_callback.py
bandwidth/models/conference_recording_available_callback.py
bandwidth/models/conference_recording_metadata.py
bandwidth/models/conference_redirect_callback.py
bandwidth_sdk-21.0.0.dist-info/LICENSE
bandwidth_sdk-21.0.0.dist-info/METADATA
bandwidth_sdk-21.0.0.dist-info/WHEEL
bandwidth_sdk-21.0.0.dist-info/top_level.txt
bandwidth_sdk-21.0.0.dist-info/RECORD
