Metadata-Version: 2.1
Name: bandwidth-sdk
Version: 21.0.0
Summary: Bandwidth
Home-page: https://dev.bandwidth.com/sdks/python
Author: Bandwidth
Author-email: letstalk@bandwidth.com
Keywords: OpenAPI,OpenAPI-Generator,Bandwidth
Requires-Python: >=3.7
License-File: LICENSE
Requires-Dist: pydantic >=2
Requires-Dist: python-dateutil >=2.8.2
Requires-Dist: typing-extensions >=4.7.1
Requires-Dist: urllib3 <3.0.0,>=2.1.0
